{
  "id": "ha-thu-o",
  "slug": "ha-thu-o",
  "name": "Hà thủ ô đỏ",
  "scientificName": "Fallopia multiflora",
  "otherNames": [
    "Thủ ô",
    "Dạ giao đằng",
    "Má ỏn"
  ],
  "group": "cu-re",
  "priceRange": "90.000 - 250.000 VNĐ/kg",
  "shortDesc": "Dây leo cuốn sống lâu năm, nổi tiếng với công dụng làm đen tóc, bổ huyết, đẹp da.",
  "image": "/images/cay/ha-thu-o.jpg",
  "media": [
    {
      "type": "youtube",
      "id": "dclGe7B9IQs",
      "title": "Cách chế biến hà thủ ô làm thuốc chuẩn (VTC16)"
    },
    {
      "type": "youtube",
      "id": "i9JS3dcbCH8",
      "title": "Hướng dẫn chi tiết làm hà thủ ô chế"
    },
    {
      "type": "youtube",
      "id": "rBmPh0FKJx0",
      "title": "Thực trạng vùng trồng & hướng phát triển (SKĐS)"
    }
  ],
  "description": "Hà thủ ô đỏ là loại thảo dược mọc hoang rải rác khắp vùng núi phía Bắc và hiện nay đang được phát triển mạnh thành vùng trồng chuyên canh rộng lớn tại Hà Giang, Sơn La. Trồng Hà thủ ô đỏ đòi hỏi giàn leo vững chắc và thời gian từ 3 đến 5 năm để có chất lượng củ nặng nhất.",
  "bioCharacteristics": "Hà thủ ô đỏ là dây leo cuốn sống nhiều năm, thân mềm màu tím đỏ, lá hình tim mọc so le. Rễ phình thành củ lớn vỏ nâu đỏ, thịt hồng đỏ nhiều bột. Cây mọc hoang và trồng ở vùng núi mát ẩm, cần giàn leo chắc chắn và đất dốc nhiều mùn.",
  "usageValue": "Củ rễ là bộ phận thu mua chính, dùng chế biến (chưng với đậu đen) làm nguyên liệu bổ huyết, làm đen tóc trong y học cổ truyền. Củ lớn vỏ đỏ sẫm cho giá trị cao nhất.",
  "stats": [
    {
      "label": "Thời gian thu hoạch",
      "value": "3 - 5 năm trở lên"
    },
    {
      "label": "Đất trồng thích hợp",
      "value": "Đất đồi dốc nhẹ, nhiều mùn ẩm"
    },
    {
      "label": "Bộ phận thu hoạch",
      "value": "Củ rễ"
    },
    {
      "label": "Nhiệt độ lý tưởng",
      "value": "15°C - 30°C"
    }
  ],
  "seasonCalendar": {
    "sow": [
      2,
      3,
      4
    ],
    "harvest": [
      11,
      12,
      1
    ]
  },
  "prices": [
    {
      "grade": "Củ tươi Loại lớn",
      "specification": "Trọng lượng củ đơn lẻ >2kg, vỏ nhẵn đỏ nâu sẫm",
      "priceRange": "180.000 - 250.000",
      "unit": "kg",
      "trend": "up"
    },
    {
      "grade": "Củ tươi Loại thường",
      "specification": "Trọng lượng củ từ 0.8kg - 1.8kg",
      "priceRange": "90.000 - 130.000",
      "unit": "kg",
      "trend": "stable"
    },
    {
      "grade": "Lát Hà thủ ô sấy",
      "specification": "Thái lát dày 3-5mm, phơi sấy đạt độ ẩm chuẩn <12%",
      "priceRange": "280.000 - 350.000",
      "unit": "kg",
      "trend": "stable"
    }
  ],
  "regions": [
    {
      "regionSlug": "tay-bac",
      "regionName": "Tây Bắc",
      "provinces": [
        "Sơn La",
        "Điện Biên"
      ],
      "outputEstimate": "200 tấn/năm",
      "popularity": "phu"
    },
    {
      "regionSlug": "dong-bac",
      "regionName": "Đông Bắc",
      "provinces": [
        "Hà Giang",
        "Cao Bằng"
      ],
      "outputEstimate": "350 tấn/năm",
      "popularity": "chinh"
    }
  ],
  "technique": {
    "season": "Trồng vụ xuân (tháng 2–4), làm giàn khi cây bắt đầu vươn dây",
    "soil": "Đất đồi dốc nhẹ, nhiều mùn ẩm, thoát nước tốt",
    "ph": "5.5 – 6.5",
    "density": "15.000 – 20.000 cây/ha có giàn leo",
    "harvestTime": "3 – 5 năm trở lên để củ đạt trọng lượng lớn",
    "yield": "Củ tươi 8 – 12 tấn/ha sau 4 năm",
    "propagation": [
      "giâm hom dây",
      "ươm hạt"
    ]
  },
  "pests": [
    {
      "pestName": "Bệnh thối củ mùa mưa",
      "level": "co-gap",
      "symptom": "Củ thâm nhũn, dây héo, nhất là khi đất úng kéo dài",
      "remedy": "Lên luống cao, khơi rãnh thoát nước, xử lý vôi và Trichoderma vào đất"
    },
    {
      "pestName": "Bọ trĩ, rệp hại đọt",
      "level": "hiem",
      "symptom": "Đọt non xoăn lại, chậm leo giàn",
      "remedy": "Phun dầu neem hoặc chế phẩm nấm ký sinh khi phát hiện sớm"
    }
  ],
  "techniquesLink": "ky-thuat-trong-ha-thu-o",
  "standards": [
    "Không nhầm lẫn với Hà thủ ô trắng (ít giá trị kinh tế hơn).",
    "Củ chắc chắn, cắt ra bên trong có màu hồng đỏ nhẹ, có chứa vân bột đặc trưng.",
    "Hàm lượng tanin và các anthranoid đạt tiêu chuẩn Dược điển Việt Nam."
  ],
  "keywordsTarget": [
    "thu mua hà thủ ô",
    "giá hà thủ ô đỏ",
    "kỹ thuật trồng hà thủ ô",
    "phân biệt hà thủ ô đỏ trắng"
  ],
  "faq": [
    {
      "question": "Làm thế nào để phân biệt Hà thủ ô đỏ và Hà thủ ô trắng?",
      "answer": "Hà thủ ô đỏ có củ giống khoai lang, vỏ ngoài màu nâu đỏ sẫm, nhiều nếp nhăn sâu, bên trong màu đỏ hồng có nhiều bột. Hà thủ ô trắng củ dài dẹt hơn, vỏ màu xám sáng, khi cắt ra có nhựa mủ màu trắng chảy ra, vị rất chát và không có công dụng bổ huyết bằng hà thủ ô đỏ."
    }
  ],
  "identification": {
    "fresh": "Củ bề ngoài thô ráp, dài 8-18 cm, đường kính 6-14 cm. Lớp vỏ ngoài màu nâu đỏ, nhưng khi cắt ngang, Phần thịt củ có màu trắng ngà hay nâu nhạt, ở giữa có ít lõi gỗ. Củ hà thủ ô tươi khi nhai thử sẽ có vị chát, đắng và hơi ngọt nhẹ.",
    "dry": "Rễ nguyên dạng củ tròn, củ dài hoặc hình thoi, không đều. Củ nhỏ để nguyên, củ to bổ đôi theo chiều dọc, hay chặt thành từng miếng, dài 6 – 15 cm, đường kính 4 – 12 cm. Mặt ngoài vỏ màu nâu đỏ, nâu hay nâu xám có những chỗ lồi lõm và các nếp nhăn. Chất cứng chắc, khó bẻ. Mặt cắt ngang có lớp bần mỏng, màu nâu sẫm; mô mềm vỏ màu đỏ hồng. Phần thịt củ có màu trắng ngà hay nâu nhạt; ở giữa có ít lõi gỗ. Mùi nhẹ, vị hơi đắng, hơi ngọt và chát."
  },
  "demandQuantity": "50 kg/tháng",
  "priorityLevel": "hot"
}
