{
  "id": "rieng-phien",
  "slug": "rieng-phien",
  "name": "Riềng phiến",
  "scientificName": "Alpinia officinarum",
  "otherNames": [],
  "group": "cu-re",
  "priceRange": "17.000 - 76.000 VNĐ/kg",
  "shortDesc": "Riềng phiến — dược liệu đang được thu mua, thu củ, rễ, nhu cầu 50 kg/tháng.",
  "image": "/images/cay/rieng-phien.webp",
  "description": "Riềng phiến hiện nằm trong danh mục dược liệu được bao tiêu thu mua thường xuyên, sản lượng cần tối thiểu 50 kg/tháng. Bà con trồng hoặc thu hái đạt chuẩn có thể kết nối bán hàng ổn định theo giá sàn công bố mỗi tuần.",
  "bioCharacteristics": "Rễ củ, dài 6- 10 cm, đường kính 3 - 5 cm, củ chia thành nhiều đốt phình to với các kích thước không đều nhau, có nhiều rễ con xung quanh.",
  "usageValue": "Củ, rễ của Riềng phiến được thu mua làm nguyên liệu bào chế cao, trà và thuốc y học cổ truyền; hàng đạt chuẩn khô sạch cho giá tốt nhất.",
  "stats": [
    {
      "label": "Bộ phận thu hoạch",
      "value": "Củ, rễ"
    },
    {
      "label": "Nhu cầu thu mua",
      "value": "50 kg/tháng"
    },
    {
      "label": "Thời gian thu hoạch",
      "value": "8 tháng sau trồng"
    },
    {
      "label": "Nhiệt độ lý tưởng",
      "value": "22°C - 34°C"
    }
  ],
  "prices": [
    {
      "grade": "Củ, rễ khô loại 1",
      "specification": "Phơi/sấy khô đều, sạch tạp chất, không mốc mối, đúng phẩm Riềng phiến.",
      "priceRange": "52.000 - 76.000",
      "unit": "kg",
      "trend": "down"
    },
    {
      "grade": "Củ, rễ tươi nguyên liệu",
      "specification": "Thu hái tươi giao ngay cho xưởng sơ chế/nấu cao, chưa qua sấy.",
      "priceRange": "17.000 - 27.000",
      "unit": "kg",
      "trend": "stable"
    }
  ],
  "regions": [
    {
      "regionSlug": "tay-nguyen",
      "regionName": "Tây Nguyên",
      "provinces": [
        "Lâm Đồng",
        "Đắk Lắk"
      ],
      "outputEstimate": "922 tấn/năm",
      "popularity": "chinh"
    },
    {
      "regionSlug": "tay-bac",
      "regionName": "Tây Bắc",
      "provinces": [
        "Sơn La"
      ],
      "outputEstimate": "272 tấn/năm",
      "popularity": "phu"
    }
  ],
  "technique": {
    "season": "Gieo trồng đầu xuân khi ẩm độ cao",
    "soil": "Đất phù sa giàu mùn, ẩm vừa",
    "ph": "5.1 – 6.4",
    "density": "21000 cây/ha",
    "harvestTime": "8 tháng sau trồng",
    "yield": "6 – 10 tấn khô/ha/năm",
    "propagation": [
      "ươm hạt",
      "tách mầm củ"
    ]
  },
  "pests": [
    {
      "pestName": "Bệnh thối rễ/héo rũ",
      "level": "co-gap",
      "symptom": "Cây héo dần, gốc thâm, rễ thối nhũn khi mưa nhiều.",
      "remedy": "Lên luống cao thoát nước, xử lý đất bằng vôi và nấm đối kháng Trichoderma."
    },
    {
      "pestName": "Sâu ăn lá",
      "level": "hiem",
      "symptom": "Lá bị cắn khuyết, xuất hiện sâu non mặt dưới lá.",
      "remedy": "Bắt thủ công, dùng bẫy và chế phẩm sinh học, hạn chế thuốc hóa học cận thu hoạch."
    }
  ],
  "techniquesLink": "ky-thuat-trong-rieng-phien",
  "standards": [
    "Sạch tạp chất, đất cát, cỏ dại và bộ phận không đúng phẩm quá 1%.",
    "Khô đều, không ẩm mốc, không mối mọt, mùi đặc trưng của dược liệu.",
    "Không tồn dư thuốc bảo vệ thực vật vượt ngưỡng, đạt tiêu chí kiểm định đầu vào của nhà máy."
  ],
  "keywordsTarget": [
    "thu mua riềng phiến",
    "giá riềng phiến",
    "bán riềng phiến khô",
    "thu mua dược liệu riềng phiến"
  ],
  "faq": [
    {
      "question": "Vietmec thu mua Riềng phiến với số lượng và tiêu chuẩn thế nào?",
      "answer": "Nhu cầu tối thiểu 50 kg/tháng, hàng cần đạt các tiêu chí khô sạch, đúng phẩm cấp củ, rễ. Bà con gửi mẫu và thông số lô hàng để được báo giá sàn theo tuần."
    }
  ],
  "identification": {
    "fresh": "Rễ củ, dài 6- 10 cm, đường kính 3 - 5 cm, củ chia thành nhiều đốt phình to với các kích thước không đều nhau, có nhiều rễ con xung quanh.",
    "dry": "Thân rễ hình trụ, thường cong và phân nhánh nhiều, dài 5 - 9 cm hoặc hơn, đường kính 2 - 4 cm. Mặt ngoài màu nâu đỏ đến nâu sẫm, có nhiều nếp nhăn dọc và những mấu vòng màu xám; mỗi mấu dài 0,2 - 1 cm, mang vết tích của rễ con. Thể chất dai, chắc, khó bẻ gẫy. Mặt gẫy màu vàng xám hay nâu đỏ. Vùng trụ chiếm 1/3 mặt cắt của thân rễ."
  },
  "demandQuantity": "50 kg/tháng",
  "priorityLevel": "hot"
}
