{
  "id": "xich-dong-nam",
  "slug": "xich-dong-nam",
  "name": "Xích đồng nam",
  "scientificName": "Clerodendrum japonicum",
  "otherNames": [],
  "group": "hoa-la",
  "priceRange": "10.000 - 53.000 VNĐ/kg",
  "shortDesc": "Xích đồng nam — dược liệu đang được thu mua, thu toàn cây trên mặt đất, nhu cầu 50 kg/tháng.",
  "image": "/images/cay/xich-dong-nam.webp",
  "description": "Xích đồng nam hiện nằm trong danh mục dược liệu được bao tiêu thu mua thường xuyên, sản lượng cần tối thiểu 50 kg/tháng. Bà con trồng hoặc thu hái đạt chuẩn có thể kết nối bán hàng ổn định theo giá sàn công bố mỗi tuần.",
  "bioCharacteristics": "Rễ hình trụ, mọc thẳng hoặc hơi cong, phân nhiều rễ con. Chiều dài từ 10 - 30 cm, đường kính khoảng 0,5 - 2 cm. ặt ngoài rễ có màu vàng xám với các vết nhăn dọc, mặt cắt ngang bên trong có màu vàng nhạt.",
  "usageValue": "Toàn cây trên mặt đất của Xích đồng nam được thu mua làm nguyên liệu bào chế cao, trà và thuốc y học cổ truyền; hàng đạt chuẩn khô sạch cho giá tốt nhất.",
  "stats": [
    {
      "label": "Bộ phận thu hoạch",
      "value": "Toàn cây trên mặt đất"
    },
    {
      "label": "Nhu cầu thu mua",
      "value": "50 kg/tháng"
    },
    {
      "label": "Thời gian thu hoạch",
      "value": "9 tháng sau trồng"
    },
    {
      "label": "Nhiệt độ lý tưởng",
      "value": "23°C - 35°C"
    }
  ],
  "prices": [
    {
      "grade": "Toàn cây trên mặt đất khô loại 1",
      "specification": "Phơi/sấy khô đều, sạch tạp chất, không mốc mối, đúng phẩm Xích đồng nam.",
      "priceRange": "30.000 - 53.000",
      "unit": "kg",
      "trend": "stable"
    },
    {
      "grade": "Toàn cây trên mặt đất tươi nguyên liệu",
      "specification": "Thu hái tươi giao ngay cho xưởng sơ chế/nấu cao, chưa qua sấy.",
      "priceRange": "10.000 - 21.000",
      "unit": "kg",
      "trend": "stable"
    }
  ],
  "regions": [
    {
      "regionSlug": "bac-trung-bo",
      "regionName": "Bắc Trung Bộ",
      "provinces": [
        "Nghệ An",
        "Thanh Hóa"
      ],
      "outputEstimate": "503 tấn/năm",
      "popularity": "chinh"
    },
    {
      "regionSlug": "tay-nguyen",
      "regionName": "Tây Nguyên",
      "provinces": [
        "Lâm Đồng"
      ],
      "outputEstimate": "353 tấn/năm",
      "popularity": "phu"
    }
  ],
  "technique": {
    "season": "Trồng quanh năm nơi chủ động tưới",
    "soil": "Đất đồi feralit thoát nước nhanh",
    "ph": "6.5 – 7.8",
    "density": "11500 cây/ha",
    "harvestTime": "9 tháng sau trồng",
    "yield": "7 – 7 tấn khô/ha/năm",
    "propagation": [
      "gieo hạt",
      "giâm cành"
    ]
  },
  "pests": [
    {
      "pestName": "Bệnh thối rễ/héo rũ",
      "level": "co-gap",
      "symptom": "Cây héo dần, gốc thâm, rễ thối nhũn khi mưa nhiều.",
      "remedy": "Lên luống cao thoát nước, xử lý đất bằng vôi và nấm đối kháng Trichoderma."
    },
    {
      "pestName": "Sâu ăn lá",
      "level": "hiem",
      "symptom": "Lá bị cắn khuyết, xuất hiện sâu non mặt dưới lá.",
      "remedy": "Bắt thủ công, dùng bẫy và chế phẩm sinh học, hạn chế thuốc hóa học cận thu hoạch."
    }
  ],
  "techniquesLink": "ky-thuat-trong-xich-dong-nam",
  "standards": [
    "Sạch tạp chất, đất cát, cỏ dại và bộ phận không đúng phẩm quá 1%.",
    "Khô đều, không ẩm mốc, không mối mọt, mùi đặc trưng của dược liệu.",
    "Không tồn dư thuốc bảo vệ thực vật vượt ngưỡng, đạt tiêu chí kiểm định đầu vào của nhà máy."
  ],
  "keywordsTarget": [
    "thu mua xích đồng nam",
    "giá xích đồng nam",
    "bán xích đồng nam khô",
    "thu mua dược liệu xích đồng nam"
  ],
  "faq": [
    {
      "question": "Vietmec thu mua Xích đồng nam với số lượng và tiêu chuẩn thế nào?",
      "answer": "Nhu cầu tối thiểu 50 kg/tháng, hàng cần đạt các tiêu chí khô sạch, đúng phẩm cấp toàn cây trên mặt đất. Bà con gửi mẫu và thông số lô hàng để được báo giá sàn theo tuần."
    }
  ],
  "identification": {
    "fresh": "Rễ hình trụ, mọc thẳng hoặc hơi cong, phân nhiều rễ con. Chiều dài từ 10 - 30 cm, đường kính khoảng 0,5 - 2 cm. ặt ngoài rễ có màu vàng xám với các vết nhăn dọc, mặt cắt ngang bên trong có màu vàng nhạt.",
    "dry": "Rễ hình trụ, thẳng hoặc hơi cong, dài 10 cm đến 30 cm, đường kính 0,5 cm đến 2 cm và có nhiều rễ con. Mặt ngoài màu vàng xám, có những vết nhăn theo chiều dọc. Mặt cắt ngang màu vàng nhạt. Chất giòn cứng, dễ bẻ gãy, mùi thơm nhẹ, vị nhạt."
  },
  "demandQuantity": "50 kg/tháng",
  "priorityLevel": "hot"
}
